metaso_sdk-0.1.6.dist-info/METADATA
metaso_sdk-0.1.6.dist-info/WHEEL
metaso_sdk-0.1.6.dist-info/entry_points.txt
metaso_sdk-0.1.6.dist-info/licenses/LICENSE
metaso_sdk/__init__.py
metaso_sdk/__main__.py
metaso_sdk/bookshelf.py
metaso_sdk/cli.py
metaso_sdk/client.py
metaso_sdk/debug.py
metaso_sdk/model.py
metaso_sdk/py.typed
metaso_sdk/search.py
metaso_sdk/subject.py
metaso_sdk-0.1.6.dist-info/RECORD
