Metadata-Version: 2.1
Name: metaso-sdk
Version: 0.1.6
Summary: The official Python SDK for https://metaso.cn
Author-Email: Zhao Xiaohong <zhaoxiaohong@metasota.ai>
License: MIT
Classifier: Development Status :: 4 - Beta
Classifier: Intended Audience :: Developers
Classifier: Programming Language :: Python
Classifier: Programming Language :: Python :: 3
Classifier: Programming Language :: Python :: 3 :: Only
Classifier: Programming Language :: Python :: 3.8
Classifier: Programming Language :: Python :: 3.9
Classifier: Programming Language :: Python :: 3.10
Classifier: Programming Language :: Python :: 3.11
Classifier: Programming Language :: Python :: 3.12
Classifier: Programming Language :: Python :: 3.13
Classifier: Topic :: Documentation
Classifier: Topic :: Software Development
Classifier: Topic :: Utilities
Classifier: Typing :: Typed
Project-URL: Homepage, https://meta-sota.github.io/metaso-sdk
Project-URL: Documentation, https://meta-sota.github.io/metaso-sdk
Project-URL: Changelog, https://meta-sota.github.io/metaso-sdk/changelog
Project-URL: Repository, https://github.com/meta-sota/metaso-sdk
Project-URL: Issues, https://github.com/meta-sota/metaso-sdk/issues
Project-URL: Discussions, https://github.com/meta-sota/metaso-sdk/discussions
Requires-Python: >=3.8
Requires-Dist: httpx-sse>=0.4.0
Requires-Dist: httpx>=0.27.2
Requires-Dist: pydantic>=2.10.0
Requires-Dist: streamable>=1.3.5
